Workbook
Name Slicer_Order_Date: #N/A

Sheet Business Insights
A1: Business Insights
A4: No | B4: Observation | C4: Recommendation
A5: 1 | B5: South region generated the highest revenue. | C5: Increase marketing in the South region.
A6: 2 | B6: Electronics is the most profitable category. | C6: Expand the electronics product range.
A7: 3 | B7: Pen is the best-selling product. | C7: Maintain higher inventory levels.
A8: 4 | B8: David achieved the highest sales. | C8: Recognize performance and share best practices.
A9: 5 | B9: Card is the preferred payment method. | C9: Improve card payment promotions.
A10: 6 | B10: Revenue peaks in certain months. | C10: Schedule promotions during those periods.
A11: 7 | B11: Average revenue per order is healthy. | C11: Introduce bundles to increase order value.
A12: 8 | B12: High-value orders drive revenue. | C12: Reward loyal high-value customers.
A13: 9 | B13: Some orders are very small. | C13: Encourage larger purchases with offers.
A14: 10 | B14: Overall business performance is positive. | C14: Continue monitoring trends and optimize strategy.
A15: The company shows strong sales performance with healthy revenue and profit. Electronics and the South region contribute significantly to business growth. Card payments are the preferred payment method, and high-performing products and salespeople should be supported with targeted promotions and inventory planning.

Sheet Dashboard
A1: RETAIL SALES DASHBOARD
A4: Total Revenue | E4: Total Profit
A6: ='Analysis '!B3 -> 7635603.5 | E6: ='Analysis '!B4 -> 2277006
A9: Average Revenue | E9: Average Profit
A11: ='Analysis '!B5 -> 7995.3963 | E11: ='Analysis '!B6 -> 2384.2995
A14: Highest Revenue | E14: Total Orders
A16: ='Analysis '!B7 -> 29850 | E16: ='Analysis '!B9 -> 955

Sheet Pivot Table
A1: Region | B1: Sum of Revenue | G1: Product | H1: Sum of Revenue | N1: Payment_Method | O1: Sum of Revenue
A2: East | B2: 4560 | G2: Cabinet | H2: 658896 | N2: Bank Transfer | O2: 1975969
A3: North | B3: 6675 | G3: Chair | H3: 600261.5 | N3: Card | O3: 1662142
A4: South | B4: 23110 | G4: Desk | H4: 602664.5 | N4: Cash | O4: 1829311.5
A5: West | B5: 12940 | G5: Marker | H5: 540189.5 | N5: UPI | O5: 2168181
A6: Grand Total | B6: 47285 | G6: Monitor | H6: 545498 | N6: Grand Total | O6: 7635603.5
G7: Mouse | H7: 552747
G8: Pen | H8: 673718
G9: Stapler | H9: 584751
A10: Category | B10: Sum of Profit | G10: Table | H10: 540882
A11: Electronics | B11: 754552 | G11: Tablet | H11: 635150.5
A12: Furniture | B12: 734769.5 | G12: Grand Total | H12: 5934758 | N12: Customer_Rating | O12: Sum of Order_ID
A13: Office | B13: 787684.5 | N13: 1 | O13: 1979250
A14: Grand Total | B14: 2277006 | N14: 2 | O14: 1867478
G15: Salesperson | H15: Sum of Revenue | N15: 3 | O15: 2120706
G16: Aisha | H16: 979373 | N16: 4 | O16: 2083000
G17: Arun | H17: 1028761.5 | N17: 5 | O17: 1983879
A18: Order_Date | B18: Sum of Revenue | G18: David | H18: 1323172 | N18: Grand Total | O18: 10034313
A19: 2024-01-01 | B19: 6296 | G19: John | H19: 1035911
A20: 2024-01-02 | B20: 15785 | G20: Meera | H20: 1127391.5
A21: 2024-01-07 | B21: 13714 | G21: Priya | H21: 1007877.5
A22: 2025-01-01 | B22: 1150 | G22: Rahul | H22: 1133117
A23: 2025-01-02 | B23: 10340 | G23: Grand Total | H23: 7635603.5
A24: Grand Total | B24: 47285

Sheet Analysis 
A1: BUSINESS SUMMARY
A3: Total Revenue | B3: =SUM(Raw_Sales_Data!K:K) -> 7635603.5
A4: Total Profit | B4: =SUM(Raw_Sales_Data!M:M) -> 2277006
A5: Average Revenue | B5: =AVERAGE(Raw_Sales_Data!K:K) -> 7995.3963
A6: Average profit | B6: =AVERAGE(Raw_Sales_Data!M:M) -> 2384.2995
A7: Hightest Revenue | B7: =MAX(Raw_Sales_Data!K:K) -> 29850
A8: Lowest Revenue | B8: =MIN(Raw_Sales_Data!K:K) -> 195.5
A9: Total Orders | B9: =COUNT(Raw_Sales_Data!A:A) -> 955
A11: REVENUE BY REGION
A12: North | B12: =SUMIF(Raw_Sales_Data!D:D,"North",Raw_Sales_Data!K:K) -> 1701005.5
A13: South | B13: =SUMIF(Raw_Sales_Data!D:D,"South",Raw_Sales_Data!K:K) -> 2138300.5
A14: East | B14: =SUMIF(Raw_Sales_Data!D:D,"East",Raw_Sales_Data!K:K) -> 1662770.5
A15: West | B15: =SUMIF(Raw_Sales_Data!D:D,"West",Raw_Sales_Data!K:K) -> 2133527
A17: REVENUE BY CATEGORY
A18: Electronics | B18: =SUMIF(Raw_Sales_Data!E:E,"Electronics",Raw_Sales_Data!K:K) -> 2517789
A19: Furniture | B19: =SUMIF(Raw_Sales_Data!E:E,"Furniture",Raw_Sales_Data!K:K) -> 2447919.5
A20: Office | B20: =SUMIF(Raw_Sales_Data!E:E,"Office",Raw_Sales_Data!K:K) -> 2669895
A22: ORDERS BY REGION
A23: North | B23: =COUNTIF(Raw_Sales_Data!D:D,"North") -> 224
A24: South | B24: =COUNTIF(Raw_Sales_Data!D:D,"South") -> 241
A25: East | B25: =COUNTIF(Raw_Sales_Data!D:D,"East") -> 220
A26: West | B26: =COUNTIF(Raw_Sales_Data!D:D,"West") -> 270
A28: AVERAGE REVENUE BY REGION
A29: North | B29: =AVERAGEIF(Raw_Sales_Data!D:D,"North",Raw_Sales_Data!K:K) -> 7593.7746
A30: South | B30: =AVERAGEIF(Raw_Sales_Data!D:D,"South",Raw_Sales_Data!K:K) -> 8872.6162
A31: East | B31: =AVERAGEIF(Raw_Sales_Data!D:D,"East",Raw_Sales_Data!K:K) -> 7558.0477
A32: West | B32: =AVERAGEIF(Raw_Sales_Data!D:D,"West",Raw_Sales_Data!K:K) -> 7901.9519
A35: North Electronics Revenue | B35: =COUNTIFS(Raw_Sales_Data!D:D,"North",Raw_Sales_Data!E:E,"Electronics") -> 65
A36: North Furniture Revenue | B36: =COUNTIFS(Raw_Sales_Data!D:D,"North",Raw_Sales_Data!E:E,"Furniture") -> 81
A37: North Office Revenue | B37: =COUNTIFS(Raw_Sales_Data!D:D,"North",Raw_Sales_Data!E:E,"Office") -> 78
A39: South Electronics Revenue | B39: =COUNTIFS(Raw_Sales_Data!D:D,"South",Raw_Sales_Data!E:E,"Electronics") -> 76
A40: South Furniture Revenue | B40: =COUNTIFS(Raw_Sales_Data!D:D,"South",Raw_Sales_Data!E:E,"Furniture") -> 75
A41: South Office Revenue | B41: =COUNTIFS(Raw_Sales_Data!D:D,"South",Raw_Sales_Data!E:E,"Office") -> 90
A43: East Electronics Revenue | B43: =COUNTIFS(Raw_Sales_Data!D:D,"East",Raw_Sales_Data!E:E,"Electronics") -> 77
A44: East Furniture Revenue | B44: =COUNTIFS(Raw_Sales_Data!D:D,"East",Raw_Sales_Data!E:E,"Furniture") -> 73
A45: East Office Revenue | B45: =COUNTIFS(Raw_Sales_Data!D:D,"East",Raw_Sales_Data!E:E,"Office") -> 70
A47: West Electronics Revenue | B47: =COUNTIFS(Raw_Sales_Data!D:D,"West",Raw_Sales_Data!E:E,"Electronics") -> 91
A48: West Furniture Revenue | B48: =COUNTIFS(Raw_Sales_Data!D:D,"West",Raw_Sales_Data!E:E,"Furniture") -> 71
A49: West Office Revenue | B49: =COUNTIFS(Raw_Sales_Data!D:D,"West",Raw_Sales_Data!E:E,"Office") -> 108

Sheet Raw_Sales_Data
A1: Order_ID | B1: Order_Date | C1: Customer_Name | D1: Region | E1: Category | F1: Product | G1: Salesperson | H1: Quantity | I1: Unit_Price | J1: Discount_% | K1: Revenue | L1: Cost | M1: Profit | N1: Payment_Method | O1: Customer_Rating | Q1: total profit | R1: =SUM(M:M) -> 2277006
A2: 10002 | B2: 45658 | C2: Vivek | D2: South | E2: Office | F2: Stapler | G2: John | H2: 14 | I2: 1770 | J2: 0 | K2: 24780 | L2: 14620 | M2: 10160 | N2: Card | O2: 1 | Q2: total revenue | R2: =SUM(K:K) -> 7635603.5
A3: 10003 | B3: 2025-03-26 | C3: Vivek | D3: North | E3: Office | F3: Pen | G3: John | H3: 4 | I3: 1560 | J3: 10 | K3: 5616 | L3: 3088 | M3: 2528 | N3: Bank Transfer | O3: 1 | Q3: average revenue | R3: =AVERAGE(K:K) -> 7995.3963
A4: 10004 | B4: 2024-12-22 | C4: Amit | D4: East | E4: Office | F4: Notebook | G4: David | H4: 1 | I4: 760 | J4: 15 | K4: 646 | L4: 400 | M4: 246 | N4: Bank Transfer | O4: 4 | Q4: average profit | R4: =AVERAGE(M:M) -> 2384.2995
A5: 10005 | B5: 2025-04-29 | C5: Anjali | D5: North | E5: Furniture | F5: Cabinet | G5: Aisha | H5: 7 | I5: 580 | J5: 0 | K5: 4060 | L5: 3329 | M5: 731 | N5: Cash | O5: 1 | Q5: Maximum Revenue | R5: =MAX(K:K) -> 29850
A6: 10006 | B6: 2025-04-03 | C6: Anjali | D6: South | E6: Furniture | F6: Chair | G6: David | H6: 2 | I6: 1240 | J6: 5 | K6: 2356 | L6: 1908 | M6: 448 | N6: Cash | O6: 2 | Q6: Minimum Revenue | R6: =MIN(K:K) -> 195.5
A7: 10008 | B7: 2024-03-05 | C7: Sara | D7: West | E7: Electronics | F7: Mouse | G7: Arun | H7: 13 | I7: 910 | J7: 20 | K7: 9464 | L7: 6814 | M7: 2650 | N7: Card | O7: 5 | Q7: Total Orders | R7: =COUNT(A:A) -> 955
A8: 10009 | B8: 2024-09-17 | C8: Vivek | D8: South | E8: Office | F8: Pen | G8: John | H8: 1 | I8: 300 | J8: 0 | K8: 300 | L8: 231 | M8: 69 | N8: Card | O8: 4
A9: 10010 | B9: 2024-02-20 | C9: Riya | D9: South | E9: Office | F9: Pen | G9: Arun | H9: 7 | I9: 1850 | J9: 20 | K9: 10360 | L9: 6630 | M9: 3730 | N9: Bank Transfer | O9: 4
A10: 10011 | B10: 2025-01-06 | C10: Neha | D10: West | E10: Electronics | F10: Laptop | G10: Priya | H10: 4 | I10: 1280 | J10: 15 | K10: 4352 | L10: 3655 | M10: 697 | N10: UPI | O10: 5
A11: 10012 | B11: 2024-12-26 | C11: Neha | D11: East | E11: Electronics | F11: Monitor | G11: Rahul | H11: 8 | I11: 1800 | J11: 15 | K11: 12240 | L11: 9669 | M11: 2571 | N11: UPI | O11: 1
A12: 10013 | B12: 2024-04-21 | C12: Vivek | D12: East | E12: Office | F12: Notebook | G12: Meera | H12: 11 | I12: 1300 | J12: 0 | K12: 14300 | L12: 9009 | M12: 5291 | N12: UPI | O12: 5
A13: 10014 | B13: 2025-02-02 | C13: Mohit | D13: South | E13: Office | F13: Marker | G13: Rahul | H13: 15 | I13: 1790 | J13: 0 | K13: 26850 | L13: 19869 | M13: 6981 | N13: UPI | O13: 1
A14: 10015 | B14: 2025-03-08 | C14: Sneha | D14: West | E14: Furniture | F14: Cabinet | G14: Meera | H14: 8 | I14: 650 | J14: 10 | K14: 4680 | L14: 3837 | M14: 843 | N14: Card | O14: 2
A15: 10017 | B15: 2024-11-11 | C15: Mohit | D15: West | E15: Furniture | F15: Cabinet | G15: John | H15: 11 | I15: 1900 | J15: 15 | K15: 17765 | L15: 11014 | M15: 6751 | N15: Bank Transfer | O15: 5
A16: 10018 | B16: 2024-08-24 | C16: Neha | D16: North | E16: Office | F16: Pen | G16: David | H16: 14 | I16: 1900 | J16: 10 | K16: 23940 | L16: 17236 | M16: 6704 | N16: Bank Transfer | O16: 4
A17: 10019 | B17: 2025-05-24 | C17: Nikhil | D17: West | E17: Electronics | F17: Tablet | G17: John | H17: 13 | I17: 1560 | J17: 0 | K17: 20280 | L17: 17238 | M17: 3042 | N17: Bank Transfer | O17: 2
A18: 10020 | B18: 2024-08-19 | C18: Vivek | D18: South | E18: Office | F18: Paper | G18: Rahul | H18: 14 | I18: 340 | J18: 10 | K18: 4284 | L18: 2613 | M18: 1671 | N18: UPI | O18: 1
A19: 10021 | B19: 2024-05-11 | C19: Sara | D19: West | E19: Electronics | F19: Mouse | G19: Meera | H19: 10 | I19: 990 | J19: 5 | K19: 9405 | L19: 7524 | M19: 1881 | N19: Card | O19: 3
... A956: 11016 | B956: 2024-01-17 | C956: Riya | D956: West | E956: Furniture | F956: Monitor | G956: Aisha | H956: 7 | I956: 250 | J956: 10 | K956: 11360 | L956: 9467 | M956: 998 | N956: Cash | O956: 4
